Workbook

Sheet Pivot_Region
B3: Values
A4: Row Labels | B4: Sum of Sales_INR | C4: Sum of Profit_INR
A5: South | B5: 65220000 | C5: 35284000
A6: North | B6: 59843150 | C6: 32681150
A7: West | B7: 32619850 | C7: 17313850
A8: Grand Total | B8: 157683000 | C8: 85279000
F19: Sales & Profit by Region

Sheet Pivot_Category
B3: Values
A4: Row Labels | B4: Sum of Sales_INR | C4: Sum of Profit_Margin_Percent | D4: Sum of Profit_INR
A5: AI & Automation | B5: 35940000 | C5: 3450.03 | D5: 19490000
A6: Analytics | B6: 10469000 | C6: 2602.67 | D6: 5454000
A7: Cloud Services | B7: 25787000 | C7: 3797.57 | D7: 13837000
A8: Development | B8: 33347700 | C8: 4494.25 | D8: 17981700
A9: IT Support | B9: 9216050 | C9: 3623.91 | D9: 4973050
A10: Security Services | B10: 13409500 | C10: 4354.94 | D10: 7319500
A11: Software License | B11: 29513750 | C11: 4482.44 | D11: 16223750
A12: Grand Total | B12: 157683000 | C12: 26805.81 | D12: 85279000
G20: Revenue & Profit by Service Category

Sheet Pivot_Monthly
B3: Values
A4: Row Labels | B4: Sum of Sales_INR | C4: Sum of Profit_INR
A5: 1 | B5: 11782000 | C5: 6422000
A6: January | B6: 11782000 | C6: 6422000
A7: 2 | B7: 8780600 | C7: 4724600
A8: February | B8: 8780600 | C8: 4724600
A9: 3 | B9: 9805000 | C9: 5157000
A10: March | B10: 9805000 | C10: 5157000
A11: 4 | B11: 8355650 | C11: 4633650
A12: April | B12: 8355650 | C12: 4633650
A13: 5 | B13: 8147200 | C13: 4489200
A14: May | B14: 8147200 | C14: 4489200
A15: 6 | B15: 9467700 | C15: 5138700
A16: June | B16: 9467700 | C16: 5138700
A17: 7 | B17: 6090200 | C17: 3230200
A18: July | B18: 6090200 | C18: 3230200
A19: 8 | B19: 8455100 | C19: 4561100 | K19: Monthly Sales Trend 2024
A20: August | B20: 8455100 | C20: 4561100
A21: 9 | B21: 11239350 | C21: 6004350
A22: September | B22: 11239350 | C22: 6004350
A23: 10 | B23: 25660100 | C23: 14047100
A24: October | B24: 25660100 | C24: 14047100
A25: 11 | B25: 23359900 | C25: 12547900
A26: November | B26: 23359900 | C26: 12547900
A27: 12 | B27: 26540200 | C27: 14323200
A28: December | B28: 26540200 | C28: 14323200
A29: Grand Total | B29: 157683000 | C29: 85279000

Sheet Pivot_Customers
B3: Values
A4: Row Labels | B4: Sum of Sales_INR | C4: Sum of Profit_INR
A5: Amazon India | B5: 7210150 | C5: 3971150
A6: Byju's Learning | B6: 5693700 | C6: 3132700
A7: CRED Fintech | B7: 5974650 | C7: 3270650
A8: Groww Invest | B8: 6277500 | C8: 3415500
A9: HCL Systems | B9: 6329750 | C9: 3438750
A10: Paytm Services | B10: 6396650 | C10: 3486650
A11: PhonePe Pay | B11: 7715300 | C11: 4178300
A12: Snapdeal Ltd | B12: 6173600 | C12: 3445600
A13: Tanishq Retail | B13: 7575850 | C13: 4044850
A14: Zomato Pvt Ltd | B14: 10854000 | C14: 6042000
A15: Grand Total | B15: 70201150 | C15: 38426150
I19: Top 10 Customers by Revenue

Sheet Orders
A1: Order_ID | B1: Order_Date | C1: Customer_ID | D1: Service_Name | E1: Service_Category | F1: Quantity | G1: Sales_INR | H1: Cost_INR | I1: Profit_INR | J1: Discount_Percent | K1: Order_Status | L1: Salesperson | M1: Payment_Mode | N1: Contract_Months | O1: Profit_Margin_Percent | P1: Avg_Order_Value | Q1: Region | R1: Month_Name | S1: Month_Number | T1: Company_Name
A2: ORD1001 | B2: 45656 | C2: C009 | D2: Penetration Testing | E2: Security Services | F2: 2 | G2: 140000 | H2: 60000 | I2: 80000 | J2: 0 | K2: Cancelled | L2: Priya Nair | M2: Net Banking | N2: 3 | O2: =ROUND((I2/G2)*100,2) -> 57.14 | P2: =ROUND(G2/F2,2) -> 70000 | Q2: =VLOOKUP(C2,Customers!$A:$D,3,0) -> South | R2: =TEXT(B2,"MMMM") -> December | S2: =MONTH(B2) -> 12 | T2: =VLOOKUP(C2,Customers!$A:$B,2,0) -> Swiggy Inc
A3: ORD1002 | B3: 45594 | C3: C001 | D3: AWS Management Package | E3: Cloud Services | F3: 2 | G3: 240000 | H3: 100000 | I3: 140000 | J3: 0 | K3: In Progress | L3: Pooja Singh | M3: Bank Transfer | N3: 6 | O3: =ROUND((I3/G3)*100,2) -> 58.33 | P3: =ROUND(G3/F3,2) -> 120000 | Q3: =VLOOKUP(C3,Customers!$A:$D,3,0) -> South | R3: =TEXT(B3,"MMMM") -> October | S3: =MONTH(B3) -> 10 | T3: =VLOOKUP(C3,Customers!$A:$B,2,0) -> Infosys Ltd
A4: ORD1003 | B4: 45624 | C4: C014 | D4: Penetration Testing | E4: Security Services | F4: 4 | G4: 252000 | H4: 120000 | I4: 132000 | J4: 10 | K4: Completed | L4: Rohit Sharma | M4: Credit Card | N4: 24 | O4: =ROUND((I4/G4)*100,2) -> 52.38 | P4: =ROUND(G4/F4,2) -> 63000 | Q4: =VLOOKUP(C4,Customers!$A:$D,3,0) -> South | R4: =TEXT(B4,"MMMM") -> November | S4: =MONTH(B4) -> 11 | T4: =VLOOKUP(C4,Customers!$A:$B,2,0) -> Meesho Network
A5: ORD1004 | B5: 45589 | C5: C025 | D5: Business Intelligence Report | E5: Analytics | F5: 1 | G5: 65000 | H5: 28000 | I5: 37000 | J5: 0 | K5: Completed | L5: Priya Nair | M5: Cheque | N5: 12 | O5: =ROUND((I5/G5)*100,2) -> 56.92 | P5: =ROUND(G5/F5,2) -> 65000 | Q5: =VLOOKUP(C5,Customers!$A:$D,3,0) -> North | R5: =TEXT(B5,"MMMM") -> October | S5: =MONTH(B5) -> 10 | T5: =VLOOKUP(C5,Customers!$A:$B,2,0) -> Snapdeal Ltd
A6: ORD1005 | B6: 45567 | C6: C024 | D6: IT Support & Maintenance | E6: IT Support | F6: 5 | G6: 175000 | H6: 75000 | I6: 100000 | J6: 0 | K6: Completed | L6: Priya Nair | M6: Net Banking | N6: 12 | O6: =ROUND((I6/G6)*100,2) -> 57.14 | P6: =ROUND(G6/F6,2) -> 35000 | Q6: =VLOOKUP(C6,Customers!$A:$D,3,0) -> North | R6: =TEXT(B6,"MMMM") -> October | S6: =MONTH(B6) -> 10 | T6: =VLOOKUP(C6,Customers!$A:$B,2,0) -> Amazon India
A7: ORD1006 | B7: 45613 | C7: C028 | D7: AI/ML Model Development | E7: AI & Automation | F7: 5 | G7: 1400000 | H7: 600000 | I7: 800000 | J7: 0 | K7: Cancelled | L7: Priya Nair | M7: Bank Transfer | N7: 6 | O7: =ROUND((I7/G7)*100,2) -> 57.14 | P7: =ROUND(G7/F7,2) -> 280000 | Q7: =VLOOKUP(C7,Customers!$A:$D,3,0) -> South | R7: =TEXT(B7,"MMMM") -> November | S7: =MONTH(B7) -> 11 | T7: =VLOOKUP(C7,Customers!$A:$B,2,0) -> Groww Invest
A8: ORD1007 | B8: 45440 | C8: C028 | D8: Penetration Testing | E8: Security Services | F8: 1 | G8: 66500 | H8: 30000 | I8: 36500 | J8: 5 | K8: Completed | L8: Sunita Pillai | M8: Cheque | N8: 6 | O8: =ROUND((I8/G8)*100,2) -> 54.89 | P8: =ROUND(G8/F8,2) -> 66500 | Q8: =VLOOKUP(C8,Customers!$A:$D,3,0) -> South | R8: =TEXT(B8,"MMMM") -> May | S8: =MONTH(B8) -> 5 | T8: =VLOOKUP(C8,Customers!$A:$B,2,0) -> Groww Invest
A9: ORD1008 | B9: 45481 | C9: C022 | D9: Firewall & Network Security | E9: Security Services | F9: 1 | G9: 45000 | H9: 20000 | I9: 25000 | J9: 10 | K9: Cancelled | L9: Amit Verma | M9: Net Banking | N9: 6 | O9: =ROUND((I9/G9)*100,2) -> 55.56 | P9: =ROUND(G9/F9,2) -> 45000 | Q9: =VLOOKUP(C9,Customers!$A:$D,3,0) -> South | R9: =TEXT(B9,"MMMM") -> July | S9: =MONTH(B9) -> 7 | T9: =VLOOKUP(C9,Customers!$A:$B,2,0) -> Myntra Fashion
A10: ORD1009 | B10: 45375 | C10: C009 | D10: Mobile App Development | E10: Development | F10: 2 | G10: 340000 | H10: 170000 | I10: 170000 | J10: 15 | K10: Completed | L10: Rohit Sharma | M10: Credit Card | N10: 3 | O10: =ROUND((I10/G10)*100,2) -> 50 | P10: =ROUND(G10/F10,2) -> 170000 | Q10: =VLOOKUP(C10,Customers!$A:$D,3,0) -> South | R10: =TEXT(B10,"MMMM") -> March | S10: =MONTH(B10) -> 3 | T10: =VLOOKUP(C10,Customers!$A:$B,2,0) -> Swiggy Inc
A11: ORD1010 | B11: 45453 | C11: C003 | D11: Cybersecurity Audit | E11: Security Services | F11: 5 | G11: 255000 | H11: 125000 | I11: 130000 | J11: 15 | K11: Completed | L11: Deepa Iyer | M11: UPI | N11: 24 | O11: =ROUND((I11/G11)*100,2) -> 50.98 | P11: =ROUND(G11/F11,2) -> 51000 | Q11: =VLOOKUP(C11,Customers!$A:$D,3,0) -> South | R11: =TEXT(B11,"MMMM") -> June | S11: =MONTH(B11) -> 6 | T11: =VLOOKUP(C11,Customers!$A:$B,2,0) -> Wipro Technologies
A12: ORD1011 | B12: 45621 | C12: C009 | D12: ERP Implementation | E12: Software License | F12: 2 | G12: 374000 | H12: 180000 | I12: 194000 | J12: 15 | K12: In Progress | L12: Arjun Mehta | M12: Cheque | N12: 24 | O12: =ROUND((I12/G12)*100,2) -> 51.87 | P12: =ROUND(G12/F12,2) -> 187000 | Q12: =VLOOKUP(C12,Customers!$A:$D,3,0) -> South | R12: =TEXT(B12,"MMMM") -> November | S12: =MONTH(B12) -> 11 | T12: =VLOOKUP(C12,Customers!$A:$B,2,0) -> Swiggy Inc
A13: ORD1012 | B13: 45590 | C13: C008 | D13: ERP Implementation | E13: Software License | F13: 5 | G13: 1045000 | H13: 450000 | I13: 595000 | J13: 5 | K13: Completed | L13: Rohit Sharma | M13: Bank Transfer | N13: 6 | O13: =ROUND((I13/G13)*100,2) -> 56.94 | P13: =ROUND(G13/F13,2) -> 209000 | Q13: =VLOOKUP(C13,Customers!$A:$D,3,0) -> North | R13: =TEXT(B13,"MMMM") -> October | S13: =MONTH(B13) -> 10 | T13: =VLOOKUP(C13,Customers!$A:$B,2,0) -> Zomato Pvt Ltd
... A501: ORD1500 | B501: 45598 | C501: C021 | D501: Cloud Infrastructure Setup | E501: Cloud Services | F501: 3 | G501: 540000 | H501: 240000 | I501: 300000 | J501: 0 | K501: Completed | L501: Sunita Pillai | M501: Net Banking | N501: 24 | O501: =ROUND((I501/G501)*100,2) -> 55.56 | P501: =ROUND(G501/F501,2) -> 180000 | Q501: =VLOOKUP(C501,Customers!$A:$D,3,0) -> West | R501: =TEXT(B501,"MMMM") -> November | S501: =MONTH(B501) -> 11 | T501: =VLOOKUP(C501,Customers!$A:$B,2,0) -> Tanishq Retail

Sheet Customers
A1: Customer_ID | B1: Company_Name | C1: Region | D1: Segment
A2: C001 | B2: Infosys Ltd | C2: South | D2: Enterprise
A3: C002 | B3: Tata Consultancy | C3: West | D3: Enterprise
A4: C003 | B4: Wipro Technologies | C4: South | D4: Enterprise
A5: C004 | B5: HCL Systems | C5: North | D5: Enterprise
A6: C005 | B6: Reliance Digital | C6: West | D6: Corporate
A7: C006 | B7: HDFC Bank | C7: West | D7: Corporate
A8: C007 | B8: ICICI Tech | C8: West | D8: Corporate
A9: C008 | B9: Zomato Pvt Ltd | C9: North | D9: Corporate
A10: C009 | B10: Swiggy Inc | C10: South | D10: Corporate
A11: C010 | B11: Byju's Learning | C11: South | D11: Corporate
A12: C011 | B12: Ola Cabs | C12: South | D12: SMB
... A31: C030 | B31: BharatPe | C31: North | D31: SMB
